pysmFISH/__init__.py
pysmFISH/_version.py
pysmFISH/counting.py
pysmFISH/dots_calling.py
pysmFISH/dots_coords_calculations.py
pysmFISH/filtering.py
pysmFISH/hdf5_utils.py
pysmFISH/io.py
pysmFISH/object_based_segmentation.py
pysmFISH/utils.py
pysmFISH/stitching_package/GlobalOptimization.py
pysmFISH/stitching_package/MicroscopeData.py
pysmFISH/stitching_package/__init__.py
pysmFISH/stitching_package/hdf5preparation.py
pysmFISH/stitching_package/hybregistration.py
pysmFISH/stitching_package/inout.py
pysmFISH/stitching_package/pairwisehelper.py
pysmFISH/stitching_package/pairwisesingle.py
pysmFISH/stitching_package/stitching.py
pysmFISH/stitching_package/tilejoining.py
pysmFISH-0.1.0.dist-info/METADATA
pysmFISH-0.1.0.dist-info/RECORD
pysmFISH-0.1.0.dist-info/WHEEL
pysmFISH-0.1.0.dist-info/entry_points.txt
pysmFISH-0.1.0.dist-info/top_level.txt
