Metadata-Version: 2.1
Name: pysmFISH
Version: 0.1.0
Summary: Analysis of large spatial transcriptomics data (osmFISH).
Home-page: https://linnarssonlab.org/osmFISH/
Author: Simone Codeluppi
Author-email: simone.codeluppi@gmail.com
License: MIT
Keywords: spatial transcriptomics,singlecell,bioinformatics,transcriptomics
Platform: UNKNOWN
Requires-Dist: numpy
Requires-Dist: scipy
Requires-Dist: scikit-image
Requires-Dist: scikit-learn
Requires-Dist: matplotlib
Requires-Dist: nd2reader (==2.1.3)
Requires-Dist: sympy
Requires-Dist: ruamel.yaml
Requires-Dist: h5py
Requires-Dist: dask
Requires-Dist: distributed
Requires-Dist: mpi4py
Requires-Dist: cython
Requires-Dist: loompy
